jaxio/__init__.py
jaxio-0.0.1.dist-info/LICENSE.txt
jaxio-0.0.1.dist-info/METADATA
jaxio-0.0.1.dist-info/WHEEL
jaxio-0.0.1.dist-info/top_level.txt
jaxio-0.0.1.dist-info/RECORD
