Metadata-Version: 2.1
Name: jaxio
Version: 0.0.1
Summary: Input pipelines for JAX, in JAX
Author: Daniel Watson
License-File: LICENSE.txt
Requires-Dist: jax
Requires-Dist: jaxlib
